read_serial/src/uart_rx.v
//////////////////////////////////////////////////////////////////////
// File Downloaded from http://www.nandland.com
//////////////////////////////////////////////////////////////////////
// This file contains the UART Receiver.  This receiver is able to
// receive 8 bits of serial data, one start bit, one stop bit,
// and no parity bit.  When receive is complete o_rx_dv will be
// driven high for one clock cycle.
// 
// Set Parameter CLKS_PER_BIT as follows:
// CLKS_PER_BIT = (Frequency of i_Clock)/(Frequency of UART)
// Example: 10 MHz Clock, 115200 baud UART
// (10000000)/(115200) = 87
  
module uart_rx 
  #(parameter CLKS_PER_BIT=1)
  (
   input        i_Clock,
   input        i_Rx_Serial,
   output       o_Rx_DV,
   output [7:0] o_Rx_Byte
   );
    
  parameter s_IDLE         = 3'b000;
  parameter s_RX_START_BIT = 3'b001;
  parameter s_RX_DATA_BITS = 3'b010;
  parameter s_RX_STOP_BIT  = 3'b011;
  parameter s_CLEANUP      = 3'b100;
   
  reg           r_Rx_Data_R = 1'b1;
  reg           r_Rx_Data   = 1'b1;
   
  reg [31:0]     r_Clock_Count = 0;
  reg [2:0]     r_Bit_Index   = 0; //8 bits total
  reg [7:0]     r_Rx_Byte     = 0;
  reg           r_Rx_DV       = 0;
  reg [2:0]     r_SM_Main     = 0;
   
  // Purpose: Double-register the incoming data.
  // This allows it to be used in the UART RX Clock Domain.
  // (It removes problems caused by metastability)
  always @(posedge i_Clock)
    begin
      r_Rx_Data_R <= i_Rx_Serial;
      r_Rx_Data   <= r_Rx_Data_R;
    end
   
   
  // Purpose: Control RX state machine
  always @(posedge i_Clock)
    begin
       
      case (r_SM_Main)
        s_IDLE :
          begin
            r_Rx_DV       <= 1'b0;
            r_Clock_Count <= 0;
            r_Bit_Index   <= 0;
             
            if (r_Rx_Data == 1'b0)          // Start bit detected
              r_SM_Main <= s_RX_START_BIT;
            else
              r_SM_Main <= s_IDLE;
          end
         
        // Check middle of start bit to make sure it's still low
        s_RX_START_BIT :
          begin
            if (r_Clock_Count == (CLKS_PER_BIT-1)/2)
              begin
                if (r_Rx_Data == 1'b0)
                  begin
                    r_Clock_Count <= 0;  // reset counter, found the middle
                    r_SM_Main     <= s_RX_DATA_BITS;
                  end
                else
                  r_SM_Main <= s_IDLE;
              end
            else
              begin
                r_Clock_Count <= r_Clock_Count + 1;
                r_SM_Main     <= s_RX_START_BIT;
              end
          end // case: s_RX_START_BIT
         
         
        // Wait CLKS_PER_BIT-1 clock cycles to sample serial data
        s_RX_DATA_BITS :
          begin
            if (r_Clock_Count < CLKS_PER_BIT-1)
              begin
                r_Clock_Count <= r_Clock_Count + 1;
                r_SM_Main     <= s_RX_DATA_BITS;
              end
            else
              begin
                r_Clock_Count          <= 0;
                r_Rx_Byte[r_Bit_Index] <= r_Rx_Data;
                 
                // Check if we have received all bits
                if (r_Bit_Index < 7)
                  begin
                    r_Bit_Index <= r_Bit_Index + 1;
                    r_SM_Main   <= s_RX_DATA_BITS;
                  end
                else
                  begin
                    r_Bit_Index <= 0;
                    r_SM_Main   <= s_RX_STOP_BIT;
                  end
              end
          end // case: s_RX_DATA_BITS
     
     
        // Receive Stop bit.  Stop bit = 1
        s_RX_STOP_BIT :
          begin
            // Wait CLKS_PER_BIT-1 clock cycles for Stop bit to finish
            if (r_Clock_Count < CLKS_PER_BIT-1)
              begin
                r_Clock_Count <= r_Clock_Count + 1;
                r_SM_Main     <= s_RX_STOP_BIT;
              end
            else
              begin
                r_Rx_DV       <= 1'b1;
                r_Clock_Count <= 0;
                r_SM_Main     <= s_CLEANUP;
              end
          end // case: s_RX_STOP_BIT
     
         
        // Stay here 1 clock
        s_CLEANUP :
          begin
            r_SM_Main <= s_IDLE;
            r_Rx_DV   <= 1'b0;
          end
         
         
        default :
          r_SM_Main <= s_IDLE;
         
      endcase
    end   
   
  assign o_Rx_DV   = r_Rx_DV;
  assign o_Rx_Byte = r_Rx_Byte;
   
endmodule // uart_rx

read_serial/src/main.v
module read_number (clk, rx, led1, led2, debug1);
    input clk;
    input rx;
    output led1;
    output led2;
    output debug1;

    reg valid = 1;

    parameter c_CLKS_PER_BIT = 1250;

    wire w_Rx_DV;
    wire [7:0] w_Rx_Byte;
    uart_rx #(.CLKS_PER_BIT(c_CLKS_PER_BIT)) UART_RX_INST(
        .i_Clock(clk),
        .i_Rx_Serial(rx),
        .o_Rx_DV(w_Rx_DV),
        .o_Rx_Byte(w_Rx_Byte)
    );

    reg [7:0] byte_index = 0;
    reg [31:0] received_int;
    always @(posedge w_Rx_DV) begin
        case (byte_index)
            0: begin
                valid <= 0;
                received_int[7:0] <= w_Rx_Byte;
                byte_index <= 1;
            end
            1: begin
                received_int[15:8] <= w_Rx_Byte;
                byte_index <= 2;
            end
            2: begin
                received_int[23:16] <= w_Rx_Byte;
                byte_index <= 3;
            end
            3: begin
                received_int[31:24] <= w_Rx_Byte;
                byte_index <= 0;
                valid <= 1;
            end
        endcase
    end

    assign led1 = !received_int[0];
    assign led2 = !received_int[1];
    assign debug1 = valid;

endmodule //read_number

arm_controller/tests/main_tb.v
//////////////////////////////////////////////////////////////////////
// File Downloaded from http://www.nandland.com
//////////////////////////////////////////////////////////////////////

// This testbench will exercise both the UART Tx and Rx.
// It sends out byte 0xAB over the transmitter
// It then exercises the receive by receiving byte 0x3F
`timescale 1ns/10ps

`include "src/main.v"
`include "src/uart_rx.v"

module main_tb ();
 
    parameter c_CLOCK_PERIOD_NS = 83; //approx
    parameter c_CLKS_PER_BIT = 1250;
    parameter c_BIT_PERIOD = 104167;

    reg r_Clock = 0;

    // Takes in input byte and serializes it 
    task UART_WRITE_BYTE;
        input [7:0] i_Data;
        integer     ii;
        begin
            // Send Start Bit
            r_Rx_Serial <= 1'b0;
            #(c_BIT_PERIOD);
            #1000;
            // Send Data Byte
            for (ii=0; ii<8; ii=ii+1) begin
                r_Rx_Serial <= i_Data[ii];
                #(c_BIT_PERIOD);
            end
            // Send Stop Bit
            r_Rx_Serial <= 1'b1;
            #(c_BIT_PERIOD);
        end
    endtask // UART_WRITE_BYTE
   
    always
        #(c_CLOCK_PERIOD_NS/2) r_Clock <= !r_Clock;

    reg r_Rx_Serial = 1;

    read_number READ_NUMBER_INST (
        .clk(r_Clock),
        .rx(r_Rx_Serial)
    );
 
    initial begin
        $dumpfile("test.vcd");
        $dumpvars(0, main_tb);
        @(posedge r_Clock)
        UART_WRITE_BYTE(8'h01);
        @(posedge r_Clock)
        UART_WRITE_BYTE(8'h02);
        @(posedge r_Clock)
        UART_WRITE_BYTE(8'h03);
        @(posedge r_Clock)
        UART_WRITE_BYTE(8'h04);
        @(posedge r_Clock)
        @(posedge r_Clock)
        @(posedge r_Clock)
        $display(READ_NUMBER_INST.received_int);
        $finish;
    end
endmodule

arm_controller/test.vcd
$date
	Tue Jul 14 14:12:52 2020
$end
$version
	Icarus Verilog
$end
$timescale
	10ps
$end
$scope module main_tb $end
$var reg 1 ! r_Clock $end
$var reg 1 " r_Rx_Serial $end
$scope module READ_NUMBER_INST $end
$var wire 1 ! clk $end
$var wire 1 # debug1 $end
$var wire 1 " rx $end
$var wire 1 $ w_Rx_DV $end
$var wire 8 % w_Rx_Byte [7:0] $end
$var wire 1 & led2 $end
$var wire 1 ' led1 $end
$var reg 8 ( byte_index [7:0] $end
$var reg 32 ) received_int [31:0] $end
$var reg 1 * valid $end
$scope module UART_RX_INST $end
$var wire 1 ! i_Clock $end
$var wire 1 " i_Rx_Serial $end
$var wire 8 + o_Rx_Byte [7:0] $end
$var wire 1 $ o_Rx_DV $end
$var reg 3 , r_Bit_Index [2:0] $end
$var reg 32 - r_Clock_Count [31:0] $end
$var reg 8 . r_Rx_Byte [7:0] $end
$var reg 1 / r_Rx_DV $end
$var reg 1 0 r_Rx_Data $end
$var reg 1 1 r_Rx_Data_R $end
$var reg 3 2 r_SM_Main [2:0] $end
$upscope $end
$upscope $end
$scope task UART_WRITE_BYTE $end
$var reg 8 3 i_Data [7:0] $end
$var integer 32 4 ii [31:0] $end
$upscope $end
$upscope $end
$enddefinitions $end
#0
$dumpvars
bx 4
bx 3
b0 2
11
10
0/
b0 .
b0 -
b0 ,
b0 +
1*
bx )
b0 (
x'
x&
b0 %
0$
1#
1"
0!
$end
#4100
0"
b1 3
1!
#8200
0!
#12300
01
1!
#16400
0!
#20500
00
1!
#24600
0!
#28700
b1 2
1!
#32800
0!
#36900
b1 -
1!
#41000
0!
#45100
b10 -
1!
#49200
0!
#53300
b11 -
1!
#57400
0!
#61500
b100 -
1!
#65600
0!
#69700
b101 -
1!
#73800
0!
#77900
b110 -
1!
#82000
0!
#86100
b111 -
1!
#90200
0!
#94300
b1000 -
1!
#98400
0!
#102500
b1001 -
1!
#106600
0!
#110700
b1010 -
1!
#114800
0!
#118900
b1011 -
1!
#123000
0!
#127100
b1100 -
1!
#131200
0!
#135300
b1101 -
1!
#139400
0!
#143500
b1110 -
1!
#147600
0!
#151700
b1111 -
1!
#155800
0!
#159900
b10000 -
1!
#164000
0!
#168100
b10001 -
1!
#172200
0!
#176300
b10010 -
1!
#180400
0!
#184500
b10011 -
1!
#188600
0!
#192700
b10100 -
1!
#196800
0!
#200900
b10101 -
1!
#205000
0!
#209100
b10110 -
1!
#213200
0!
#217300
b10111 -
1!
#221400
0!
#225500
b11000 -
1!
#229600
0!
#233700
b11001 -
1!
#237800
0!
#241900
b11010 -
1!
#246000
0!
#250100
b11011 -
1!
#254200
0!
#258300
b11100 -
1!
#262400
0!
#266500
b11101 -
1!
#270600
0!
#274700
b11110 -
1!
#278800
0!
#282900
b11111 -
1!
#287000
0!
#291100
b100000 -
1!
#295200
0!
#299300
b100001 -
1!
#303400
0!
#307500
b100010 -
1!
#311600
0!
#315700
b100011 -
1!
#319800
0!
#323900
b100100 -
1!
#328000
0!
#332100
b100101 -
1!
#336200
0!
#340300
b100110 -
1!
#344400
0!
#348500
b100111 -
1!
#352600
0!
#356700
b101000 -
1!
#360800
0!
#364900
b101001 -
1!
#369000
0!
#373100
b101010 -
1!
#377200
0!
#381300
b101011 -
1!
#385400
0!
#389500
b101100 -
1!
#393600
0!
#397700
b101101 -
1!
#401800
0!
#405900
b101110 -
1!
#410000
0!
#414100
b101111 -
1!
#418200
0!
#422300
b110000 -
1!
#426400
0!
#430500
b110001 -
1!
#434600
0!
#438700
b110010 -
1!
#442800
0!
#446900
b110011 -
1!
#451000
0!
#455100
b110100 -
1!
#459200
0!
#463300
b110101 -
1!
#467400
0!
#471500
b110110 -
1!
#475600
0!
#479700
b110111 -
1!
#483800
0!
#487900
b111000 -
1!
#492000
0!
#496100
b111001 -
1!
#500200
0!
#504300
b111010 -
1!
#508400
0!
#512500
b111011 -
1!
#516600
0!
#520700
b111100 -
1!
#524800
0!
#528900
b111101 -
1!
#533000
0!
#537100
b111110 -
1!
#541200
0!
#545300
b111111 -
1!
#549400
0!
#553500
b1000000 -
1!
#557600
0!
#561700
b1000001 -
1!
#565800
0!
#569900
b1000010 -
1!
#574000
0!
#578100
b1000011 -
1!
#582200
0!
#586300
b1000100 -
1!
#590400
0!
#594500
b1000101 -
1!
#598600
0!
#602700
b1000110 -
1!
#606800
0!
#610900
b1000111 -
1!
#615000
0!
#619100
b1001000 -
1!
#623200
0!
#627300
b1001001 -
1!
#631400
0!
#635500
b1001010 -
1!
#639600
0!
#643700
b1001011 -
1!
#647800
0!
#651900
b1001100 -
1!
#656000
0!
#660100
b1001101 -
1!
#664200
0!
#668300
b1001110 -
1!
#672400
0!
#676500
b1001111 -
1!
#680600
0!
#684700
b1010000 -
1!
#688800
0!
#692900
b1010001 -
1!
#697000
0!
#701100
b1010010 -
1!
#705200
0!
#709300
b1010011 -
1!
#713400
0!
#717500
b1010100 -
1!
#721600
0!
#725700
b1010101 -
1!
#729800
0!
#733900
b1010110 -
1!
#738000
0!
#742100
b1010111 -
1!
#746200
0!
#750300
b1011000 -
1!
#754400
0!
#758500
b1011001 -
1!
#762600
0!
#766700
b1011010 -
1!
#770800
0!
#774900
b1011011 -
1!
#779000
0!
#783100
b1011100 -
1!
#787200
0!
#791300
b1011101 -
1!
#795400
0!
#799500
b1011110 -
1!
#803600
0!
#807700
b1011111 -
1!
#811800
0!
#815900
b1100000 -
1!
#820000
0!
#824100
b1100001 -
1!
#828200
0!
#832300
b1100010 -
1!
#836400
0!
#840500
b1100011 -
1!
#844600
0!
#848700
b1100100 -
1!
#852800
0!
#856900
b1100101 -
1!
#861000
0!
#865100
b1100110 -
1!
#869200
0!
#873300
b1100111 -
1!
#877400
0!
#881500
b1101000 -
1!
#885600
0!
#889700
b1101001 -
1!
#893800
0!
#897900
b1101010 -
1!
#902000
0!
#906100
b1101011 -
1!
#910200
0!
#914300
b1101100 -
1!
#918400
0!
#922500
b1101101 -
1!
#926600
0!
#930700
b1101110 -
1!
#934800
0!
#938900
b1101111 -
1!
#943000
0!
#947100
b1110000 -
1!
#951200
0!
#955300
b1110001 -
1!
#959400
0!
#963500
b1110010 -
1!
#967600
0!
#971700
b1110011 -
1!
#975800
0!
#979900
b1110100 -
1!
#984000
0!
#988100
b1110101 -
1!
#992200
0!
#996300
b1110110 -
1!
#1000400
0!
#1004500
b1110111 -
1!
#1008600
0!
#1012700
b1111000 -
1!
#1016800
0!
#1020900
b1111001 -
1!
#1025000
0!
#1029100
b1111010 -
1!
#1033200
0!
#1037300
b1111011 -
1!
#1041400
0!
#1045500
b1111100 -
1!
#1049600
0!
#1053700
b1111101 -
1!
#1057800
0!
#1061900
b1111110 -
1!
#1066000
0!
#1070100
b1111111 -
1!
#1074200
0!
#1078300
b10000000 -
1!
#1082400
0!
#1086500
b10000001 -
1!
#1090600
0!
#1094700
b10000010 -
1!
#1098800
0!
#1102900
b10000011 -
1!
#1107000
0!
#1111100
b10000100 -
1!
#1115200
0!
#1119300
b10000101 -
1!
#1123400
0!
#1127500
b10000110 -
1!
#1131600
0!
#1135700
b10000111 -
1!
#1139800
0!
#1143900
b10001000 -
1!
#1148000
0!
#1152100
b10001001 -
1!
#1156200
0!
#1160300
b10001010 -
1!
#1164400
0!
#1168500
b10001011 -
1!
#1172600
0!
#1176700
b10001100 -
1!
#1180800
0!
#1184900
b10001101 -
1!
#1189000
0!
#1193100
b10001110 -
1!
#1197200
0!
#1201300
b10001111 -
1!
#1205400
0!
#1209500
b10010000 -
1!
#1213600
0!
#1217700
b10010001 -
1!
#1221800
0!
#1225900
b10010010 -
1!
#1230000
0!
#1234100
b10010011 -
1!
#1238200
0!
#1242300
b10010100 -
1!
#1246400
0!
#1250500
b10010101 -
1!
#1254600
0!
#1258700
b10010110 -
1!
#1262800
0!
#1266900
b10010111 -
1!
#1271000
0!
#1275100
b10011000 -
1!
#1279200
0!
#1283300
b10011001 -
1!
#1287400
0!
#1291500
b10011010 -
1!
#1295600
0!
#1299700
b10011011 -
1!
#1303800
0!
#1307900
b10011100 -
1!
#1312000
0!
#1316100
b10011101 -
1!
#1320200
0!
#1324300
b10011110 -
1!
#1328400
0!
#1332500
b10011111 -
1!
#1336600
0!
#1340700
b10100000 -
1!
#1344800
0!
#1348900
b10100001 -
1!
#1353000
0!
#1357100
b10100010 -
1!
#1361200
0!
#1365300
b10100011 -
1!
#1369400
0!
#1373500
b10100100 -
1!
#1377600
0!
#1381700
b10100101 -
1!
#1385800
0!
#1389900
b10100110 -
1!
#1394000
0!
#1398100
b10100111 -
1!
#1402200
0!
#1406300
b10101000 -
1!
#1410400
0!
#1414500
b10101001 -
1!
#1418600
0!
#1422700
b10101010 -
1!
#1426800
0!
#1430900
b10101011 -
1!
#1435000
0!
#1439100
b10101100 -
1!
#1443200
0!
#1447300
b10101101 -
1!
#1451400
0!
#1455500
b10101110 -
1!
#1459600
0!
#1463700
b10101111 -
1!
#1467800
0!
#1471900
b10110000 -
1!
#1476000
0!
#1480100
b10110001 -
1!
#1484200
0!
#1488300
b10110010 -
1!
#1492400
0!
#1496500
b10110011 -
1!
#1500600
0!
#1504700
b10110100 -
1!
#1508800
0!
#1512900
b10110101 -
1!
#1517000
0!
#1521100
b10110110 -
1!
#1525200
0!
#1529300
b10110111 -
1!
#1533400
0!
#1537500
b10111000 -
1!
#1541600
0!
#1545700
b10111001 -
1!
#1549800
0!
#1553900
b10111010 -
1!
#1558000
0!
#1562100
b10111011 -
1!
#1566200
0!
#1570300
b10111100 -
1!
#1574400
0!
#1578500
b10111101 -
1!
#1582600
0!
#1586700
b10111110 -
1!
#1590800
0!
#1594900
b10111111 -
1!
#1599000
0!
#1603100
b11000000 -
1!
#1607200
0!
#1611300
b11000001 -
1!
#1615400
0!
#1619500
b11000010 -
1!
#1623600
0!
#1627700
b11000011 -
1!
#1631800
0!
#1635900
b11000100 -
1!
#1640000
0!
#1644100
b11000101 -
1!
#1648200
0!
#1652300
b11000110 -
1!
#1656400
0!
#1660500
b11000111 -
1!
#1664600
0!
#1668700
b11001000 -
1!
#1672800
0!
#1676900
b11001001 -
1!
#1681000
0!
#1685100
b11001010 -
1!
#1689200
0!
#1693300
b11001011 -
1!
#1697400
0!
#1701500
b11001100 -
1!
#1705600
0!
#1709700
b11001101 -
1!
#1713800
0!
#1717900
b11001110 -
1!
#1722000
0!
#1726100
b11001111 -
1!
#1730200
0!
#1734300
b11010000 -
1!
#1738400
0!
#1742500
b11010001 -
1!
#1746600
0!
#1750700
b11010010 -
1!
#1754800
0!
#1758900
b11010011 -
1!
#1763000
0!
#1767100
b11010100 -
1!
#1771200
0!
#1775300
b11010101 -
1!
#1779400
0!
#1783500
b11010110 -
1!
#1787600
0!
#1791700
b11010111 -
1!
#1795800
0!
#1799900
b11011000 -
1!
#1804000
0!
#1808100
b11011001 -
1!
#1812200
0!
#1816300
b11011010 -
1!
#1820400
0!
#1824500
b11011011 -
1!
#1828600
0!
#1832700
b11011100 -
1!
#1836800
0!
#1840900
b11011101 -
1!
#1845000
0!
#1849100
b11011110 -
1!
#1853200
0!
#1857300
b11011111 -
1!
#1861400
0!
#1865500
b11100000 -
1!
#1869600
0!
#1873700
b11100001 -
1!
#1877800
0!
#1881900
b11100010 -
1!
#1886000
0!
#1890100
b11100011 -
1!
#1894200
0!
#1898300
b11100100 -
1!
#1902400
0!
#1906500
b11100101 -
1!
#1910600
0!
#1914700
b11100110 -
1!
#1918800
0!
#1922900
b11100111 -
1!
#1927000
0!
#1931100
b11101000 -
1!
#1935200
0!
#1939300
b11101001 -
1!
#1943400
0!
#1947500
b11101010 -
1!
#1951600
0!
#1955700
b11101011 -
1!
#1959800
0!
#1963900
b11101100 -
1!
#1968000
0!
#1972100
b11101101 -
1!
#1976200
0!
#1980300
b11101110 -
1!
#1984400
0!
#1988500
b11101111 -
1!
#1992600
0!
#1996700
b11110000 -
1!
#2000800
0!
#2004900
b11110001 -
1!
#2009000
0!
#2013100
b11110010 -
1!
#2017200
0!
#2021300
b11110011 -
1!
#2025400
0!
#2029500
b11110100 -
1!
#2033600
0!
#2037700
b11110101 -
1!
#2041800
0!
#2045900
b11110110 -
1!
#2050000
0!
#2054100
b11110111 -
1!
#2058200
0!
#2062300
b11111000 -
1!
#2066400
0!
#2070500
b11111001 -
1!
#2074600
0!
#2078700
b11111010 -
1!
#2082800
0!
#2086900
b11111011 -
1!
#2091000
0!
#2095100
b11111100 -
1!
#2099200
0!
#2103300
b11111101 -
1!
#2107400
0!
#2111500
b11111110 -
1!
#2115600
0!
#2119700
b11111111 -
1!
#2123800
0!
#2127900
b100000000 -
1!
#2132000
0!
#2136100
b100000001 -
1!
#2140200
0!
#2144300
b100000010 -
1!
#2148400
0!
#2152500
b100000011 -
1!
#2156600
0!
#2160700
b100000100 -
1!
#2164800
0!
#2168900
b100000101 -
1!
#2173000
0!
#2177100
b100000110 -
1!
#2181200
0!
#2185300
b100000111 -
1!
#2189400
0!
#2193500
b100001000 -
1!
#2197600
0!
#2201700
b100001001 -
1!
#2205800
0!
#2209900
b100001010 -
1!
#2214000
0!
#2218100
b100001011 -
1!
#2222200
0!
#2226300
b100001100 -
1!
#2230400
0!
#2234500
b100001101 -
1!
#2238600
0!
#2242700
b100001110 -
1!
#2246800
0!
#2250900
b100001111 -
1!
#2255000
0!
#2259100
b100010000 -
1!
#2263200
0!
#2267300
b100010001 -
1!
#2271400
0!
#2275500
b100010010 -
1!
#2279600
0!
#2283700
b100010011 -
1!
#2287800
0!
#2291900
b100010100 -
1!
#2296000
0!
#2300100
b100010101 -
1!
#2304200
0!
#2308300
b100010110 -
1!
#2312400
0!
#2316500
b100010111 -
1!
#2320600
0!
#2324700
b100011000 -
1!
#2328800
0!
#2332900
b100011001 -
1!
#2337000
0!
#2341100
b100011010 -
1!
#2345200
0!
#2349300
b100011011 -
1!
#2353400
0!
#2357500
b100011100 -
1!
#2361600
0!
#2365700
b100011101 -
1!
#2369800
0!
#2373900
b100011110 -
1!
#2378000
0!
#2382100
b100011111 -
1!
#2386200
0!
#2390300
b100100000 -
1!
#2394400
0!
#2398500
b100100001 -
1!
#2402600
0!
#2406700
b100100010 -
1!
#2410800
0!
#2414900
b100100011 -
1!
#2419000
0!
#2423100
b100100100 -
1!
#2427200
0!
#2431300
b100100101 -
1!
#2435400
0!
#2439500
b100100110 -
1!
#2443600
0!
#2447700
b100100111 -
1!
#2451800
0!
#2455900
b100101000 -
1!
#2460000
0!
#2464100
b100101001 -
1!
#2468200
0!
#2472300
b100101010 -
1!
#2476400
0!
#2480500
b100101011 -
1!
#2484600
0!
#2488700
b100101100 -
1!
#2492800
0!
#2496900
b100101101 -
1!
#2501000
0!
#2505100
b100101110 -
1!
#2509200
0!
#2513300
b100101111 -
1!
#2517400
0!
#2521500
b100110000 -
1!
#2525600
0!
#2529700
b100110001 -
1!
#2533800
0!
#2537900
b100110010 -
1!
#2542000
0!
#2546100
b100110011 -
1!
#2550200
0!
#2554300
b100110100 -
1!
#2558400
0!
#2562500
b100110101 -
1!
#2566600
0!
#2570700
b100110110 -
1!
#2574800
0!
#2578900
b100110111 -
1!
#2583000
0!
#2587100
b100111000 -
1!
#2591200
0!
#2595300
b100111001 -
1!
#2599400
0!
#2603500
b100111010 -
1!
#2607600
0!
#2611700
b100111011 -
1!
#2615800
0!
#2619900
b100111100 -
1!
#2624000
0!
#2628100
b100111101 -
1!
#2632200
0!
#2636300
b100111110 -
1!
#2640400
0!
#2644500
b100111111 -
1!
#2648600
0!
#2652700
b101000000 -
1!
#2656800
0!
#2660900
b101000001 -
1!
#2665000
0!
#2669100
b101000010 -
1!
#2673200
0!
#2677300
b101000011 -
1!
#2681400
0!
#2685500
b101000100 -
1!
#2689600
0!
#2693700
b101000101 -
1!
#2697800
0!
#2701900
b101000110 -
1!
#2706000
0!
#2710100
b101000111 -
1!
#2714200
0!
#2718300
b101001000 -
1!
#2722400
0!
#2726500
b101001001 -
1!
#2730600
0!
#2734700
b101001010 -
1!
#2738800
0!
#2742900
b101001011 -
1!
#2747000
0!
#2751100
b101001100 -
1!
#2755200
0!
#2759300
b101001101 -
1!
#2763400
0!
#2767500
b101001110 -
1!
#2771600
0!
#2775700
b101001111 -
1!
#2779800
0!
#2783900
b101010000 -
1!
#2788000
0!
#2792100
b101010001 -
1!
#2796200
0!
#2800300
b101010010 -
1!
#2804400
0!
#2808500
b101010011 -
1!
#2812600
0!
#2816700
b101010100 -
1!
#2820800
0!
#2824900
b101010101 -
1!
#2829000
0!
#2833100
b101010110 -
1!
#2837200
0!
#2841300
b101010111 -
1!
#2845400
0!
#2849500
b101011000 -
1!
#2853600
0!
#2857700
b101011001 -
1!
#2861800
0!
#2865900
b101011010 -
1!
#2870000
0!
#2874100
b101011011 -
1!
#2878200
0!
#2882300
b101011100 -
1!
#2886400
0!
#2890500
b101011101 -
1!
#2894600
0!
#2898700
b101011110 -
1!
#2902800
0!
#2906900
b101011111 -
1!
#2911000
0!
#2915100
b101100000 -
1!
#2919200
0!
#2923300
b101100001 -
1!
#2927400
0!
#2931500
b101100010 -
1!
#2935600
0!
#2939700
b101100011 -
1!
#2943800
0!
#2947900
b101100100 -
1!
#2952000
0!
#2956100
b101100101 -
1!
#2960200
0!
#2964300
b101100110 -
1!
#2968400
0!
#2972500
b101100111 -
1!
#2976600
0!
#2980700
b101101000 -
1!
#2984800
0!
#2988900
b101101001 -
1!
#2993000
0!
#2997100
b101101010 -
1!
#3001200
0!
#3005300
b101101011 -
1!
#3009400
0!
#3013500
b101101100 -
1!
#3017600
0!
#3021700
b101101101 -
1!
#3025800
0!
#3029900
b101101110 -
1!
#3034000
0!
#3038100
b101101111 -
1!
#3042200
0!
#3046300
b101110000 -
1!
#3050400
0!
#3054500
b101110001 -
1!
#3058600
0!
#3062700
b101110010 -
1!
#3066800
0!
#3070900
b101110011 -
1!
#3075000
0!
#3079100
b101110100 -
1!
#3083200
0!
#3087300
b101110101 -
1!
#3091400
0!
#3095500
b101110110 -
1!
#3099600
0!
#3103700
b101110111 -
1!
#3107800
0!
#3111900
b101111000 -
1!
#3116000
0!
#3120100
b101111001 -
1!
#3124200
0!
#3128300
b101111010 -
1!
#3132400
0!
#3136500
b101111011 -
1!
#3140600
0!
#3144700
b101111100 -
1!
#3148800
0!
#3152900
b101111101 -
1!
#3157000
0!
#3161100
b101111110 -
1!
#3165200
0!
#3169300
b101111111 -
1!
#3173400
0!
#3177500
b110000000 -
1!
#3181600
0!
#3185700
b110000001 -
1!
#3189800
0!
#3193900
b110000010 -
1!
#3198000
0!
#3202100
b110000011 -
1!
#3206200
0!
#3210300
b110000100 -
1!
#3214400
0!
#3218500
b110000101 -
1!
#3222600
0!
#3226700
b110000110 -
1!
#3230800
0!
#3234900
b110000111 -
1!
#3239000
0!
#3243100
b110001000 -
1!
#3247200
0!
#3251300
b110001001 -
1!
#3255400
0!
#3259500
b110001010 -
1!
#3263600
0!
#3267700
b110001011 -
1!
#3271800
0!
#3275900
b110001100 -
1!
#3280000
0!
#3284100
b110001101 -
1!
#3288200
0!
#3292300
b110001110 -
1!
#3296400
0!
#3300500
b110001111 -
1!
#3304600
0!
#3308700
b110010000 -
1!
#3312800
0!
#3316900
b110010001 -
1!
#3321000
0!
#3325100
b110010010 -
1!
#3329200
0!
#3333300
b110010011 -
1!
#3337400
0!
#3341500
b110010100 -
1!
#3345600
0!
#3349700
b110010101 -
1!
#3353800
0!
#3357900
b110010110 -
1!
#3362000
0!
#3366100
b110010111 -
1!
#3370200
0!
#3374300
b110011000 -
1!
#3378400
0!
#3382500
b110011001 -
1!
#3386600
0!
#3390700
b110011010 -
1!
#3394800
0!
#3398900
b110011011 -
1!
#3403000
0!
#3407100
b110011100 -
1!
#3411200
0!
#3415300
b110011101 -
1!
#3419400
0!
#3423500
b110011110 -
1!
#3427600
0!
#3431700
b110011111 -
1!
#3435800
0!
#3439900
b110100000 -
1!
#3444000
0!
#3448100
b110100001 -
1!
#3452200
0!
#3456300
b110100010 -
1!
#3460400
0!
#3464500
b110100011 -
1!
#3468600
0!
#3472700
b110100100 -
1!
#3476800
0!
#3480900
b110100101 -
1!
#3485000
0!
#3489100
b110100110 -
1!
#3493200
0!
#3497300
b110100111 -
1!
#3501400
0!
#3505500
b110101000 -
1!
#3509600
0!
#3513700
b110101001 -
1!
#3517800
0!
#3521900
b110101010 -
1!
#3526000
0!
#3530100
b110101011 -
1!
#3534200
0!
#3538300
b110101100 -
1!
#3542400
0!
#3546500
b110101101 -
1!
#3550600
0!
#3554700
b110101110 -
1!
#3558800
0!
#3562900
b110101111 -
1!
#3567000
0!
#3571100
b110110000 -
1!
#3575200
0!
#3579300
b110110001 -
1!
#3583400
0!
#3587500
b110110010 -
1!
#3591600
0!
#3595700
b110110011 -
1!
#3599800
0!
#3603900
b110110100 -
1!
#3608000
0!
#3612100
b110110101 -
1!
#3616200
0!
#3620300
b110110110 -
1!
#3624400
0!
#3628500
b110110111 -
1!
#3632600
0!
#3636700
b110111000 -
1!
#3640800
0!
#3644900
b110111001 -
1!
#3649000
0!
#3653100
b110111010 -
1!
#3657200
0!
#3661300
b110111011 -
1!
#3665400
0!
#3669500
b110111100 -
1!
#3673600
0!
#3677700
b110111101 -
1!
#3681800
0!
#3685900
b110111110 -
1!
#3690000
0!
#3694100
b110111111 -
1!
#3698200
0!
#3702300
b111000000 -
1!
#3706400
0!
#3710500
b111000001 -
1!
#3714600
0!
#3718700
b111000010 -
1!
#3722800
0!
#3726900
b111000011 -
1!
#3731000
0!
#3735100
b111000100 -
1!
#3739200
0!
#3743300
b111000101 -
1!
#3747400
0!
#3751500
b111000110 -
1!
#3755600
0!
#3759700
b111000111 -
1!
#3763800
0!
#3767900
b111001000 -
1!
#3772000
0!
#3776100
b111001001 -
1!
#3780200
0!
#3784300
b111001010 -
1!
#3788400
0!
#3792500
b111001011 -
1!
#3796600
0!
#3800700
b111001100 -
1!
#3804800
0!
#3808900
b111001101 -
1!
#3813000
0!
#3817100
b111001110 -
1!
#3821200
0!
#3825300
b111001111 -
1!
#3829400
0!
#3833500
b111010000 -
1!
#3837600
0!
#3841700
b111010001 -
1!
#3845800
0!
#3849900
b111010010 -
1!
#3854000
0!
#3858100
b111010011 -
1!
#3862200
0!
#3866300
b111010100 -
1!
#3870400
0!
#3874500
b111010101 -
1!
#3878600
0!
#3882700
b111010110 -
1!
#3886800
0!
#3890900
b111010111 -
1!
#3895000
0!
#3899100
b111011000 -
1!
#3903200
0!
#3907300
b111011001 -
1!
#3911400
0!
#3915500
b111011010 -
1!
#3919600
0!
#3923700
b111011011 -
1!
#3927800
0!
#3931900
b111011100 -
1!
#3936000
0!
#3940100
b111011101 -
1!
#3944200
0!
#3948300
b111011110 -
1!
#3952400
0!
#3956500
b111011111 -
1!
#3960600
0!
#3964700
b111100000 -
1!
#3968800
0!
#3972900
b111100001 -
1!
#3977000
0!
#3981100
b111100010 -
1!
#3985200
0!
#3989300
b111100011 -
1!
